meitorch/__init__.py
meitorch/analyze.py
meitorch/linearmei.py
meitorch/mei.py
meitorch/result.py
meitorch/objective/__init__.py
meitorch/objective/deepdraw.py
meitorch/objective/gabor.py
meitorch/objective/objective_reguralization.py
meitorch/objective/optimizer.py
meitorch/tools/__init__.py
meitorch/tools/base_transforms.py
meitorch/tools/denoisers.py
meitorch/tools/distributions.py
meitorch/tools/generator_nn.py
meitorch/tools/masks.py
meitorch/tools/precond.py
meitorch/tools/schedules.py
meitorch/tools/transformations.py
meitorch/tools/transforms.py
meitorch/tools/utils.py
meitorch-0.223.dist-info/LICENSE.txt
meitorch-0.223.dist-info/METADATA
meitorch-0.223.dist-info/WHEEL
meitorch-0.223.dist-info/top_level.txt
meitorch-0.223.dist-info/RECORD
